authivate/__init__.py
authivate/src/__init__.py
authivate/src/authivate.py
authivate/src/models/__init__.py
authivate/src/models/user_record.py
authivate/src/utils/__init__.py
authivate/src/utils/authivate_config.py
authivate/src/utils/authivate_exception.py
authivate/src/utils/authivate_response.py
authivate-0.2.2.dist-info/LICENSE
authivate-0.2.2.dist-info/METADATA
authivate-0.2.2.dist-info/WHEEL
authivate-0.2.2.dist-info/RECORD
